{
    "version": "https://jsonfeed.org/version/1",
    "title": "AREA-51",
    "description": "",
    "home_page_url": "https://area-51.cz",
    "feed_url": "https://area-51.cz/feed.json",
    "user_comment": "",
    "author": {
        "name": "Jan Rippl"
    },
    "items": [
        {
            "id": "https://area-51.cz/publii.html",
            "url": "https://area-51.cz/publii.html",
            "title": "Publii",
            "summary": "Publii CMS",
            "content_html": "<p>Publii CMS</p>",
            "author": {
                "name": "Jan Rippl"
            },
            "tags": [
            ],
            "date_published": "2023-06-18T12:12:16+02:00",
            "date_modified": "2023-06-18T12:12:16+02:00"
        },
        {
            "id": "https://area-51.cz/pripravujeme.html",
            "url": "https://area-51.cz/pripravujeme.html",
            "title": "Připravujeme...",
            "summary": "Připravuji celou řadu internetových projektů, jenž jsou v tuto chvíli z větší či menší části rozpracovány, některé z nich pak v jejich základní podobě téměř dokončeny. A51, neblo-li AREA - 51, je název mého úložiště programových skriptů na službě github, jenž využívám pro své projekty.",
            "content_html": "<p>Připravuji celou řadu internetových projektů, jenž jsou v tuto chvíli z větší či menší části rozpracovány, některé z nich pak v jejich základní podobě téměř dokončeny.</p>\n<figure class=\"post__image post__image--left\"><img loading=\"lazy\"  style=\"outline: 3px solid rgba(var(--color-primary-rgb), 0.55)  !important;\" src=\"https://area-51.cz/media/posts/1/alien3-2.png\" alt=\"\" width=\"2000\" height=\"2000\" sizes=\"100vw\" srcset=\"https://area-51.cz/media/posts/1/responsive/alien3-2-xs.png 300w ,https://area-51.cz/media/posts/1/responsive/alien3-2-sm.png 480w ,https://area-51.cz/media/posts/1/responsive/alien3-2-md.png 768w ,https://area-51.cz/media/posts/1/responsive/alien3-2-lg.png 1024w ,https://area-51.cz/media/posts/1/responsive/alien3-2-xl.png 1360w ,https://area-51.cz/media/posts/1/responsive/alien3-2-2xl.png 1600w\"></figure>\n<p class=\"dropcap\">A51, neblo-li AREA - 51, je název mého úložiště programových skriptů na službě <a href=\"https://github.com/\" target=\"_blank\" rel=\"noopener noreferrer\">github</a>, jenž využívám pro své projekty. Rovněž zde sídlí i tento web, jenž jako jediný provozuji mimo svůj server.</p>\n<p>To má své opodstatnění pro případ, kdy dojde na příslušném serveru k například k výpadku, a je nutné o tom informovat...</p>\n<p style=\"clear: both;\"> </p>\n<blockquote>\n<p>Oblast 51 (Area 51)</p>\n<p>Katastrální území státu Nevada (USA), jehož součástí je i vyschlé Groomovo jezero (Groom Lake), na jehož dně bylo vybudováno přísně tajné testovací zařízení pod kódem ICAO KXTA - tzv. Homey Airport (Dreamland - Země snů) s nejdelší přistávací dráhou na světě...</p>\n</blockquote>\n<h4>Povaha projektu</h4>\n<p>AREA-51 byla v dobách své největší slávy zejména testovacím polygonem pro nejrůznější demonstrátory budoucích prototypů leteckých prostředků letectva armády Spojených států amerických.</p>\n<p>Později dle výpovědí bývalých členů ostrahy Groom Lake se později tato přísně utajovaná základna taktického letectva stala spíše skladištěm, přičemž většina pozdějších testů (průletů) se týkala letecké techniky, která ani nebyla v tomto prostoru dislokována (nad oblastí pouze proletěla), což je logické, neboť drtivá většina těchto strojů je vyvíjena soukromým sektorem, a tudíž je skladována v areálech právě těchto firem...</p>\n<p>A právě area-51.cz, tedy i tento web, společně se zkopírovanými repozitáři jsou \"uskladněny\" zde na službě GITHUB, avšak testovány někde úplně jinde. To čím se zabývám já, je ve své podstatě tzv. reverzní inženýrství softwarových nástrojů, jenž jsou k dispozici pod svobodnými licencemi.</p>\n<h4>Cíle projektu</h4>\n<p>text</p>\n<ol class=\"ordered-list\">\n<li>text A</li>\n</ol>\n<table style=\"border-collapse: collapse; width: 100%; height: 402.875px;\" border=\"1\"><caption>Seznam webových projektů:</caption>\n<tbody>\n<tr style=\"height: 50.3594px;\">\n<td style=\"width: 33.2843%; height: 50.3594px;\"><strong>Doména:</strong></td>\n<td style=\"width: 33.2843%; height: 50.3594px;\"><strong>Zaměření:</strong></td>\n<td style=\"width: 33.2889%; height: 50.3594px;\"><strong>Hotovo (%):</strong></td>\n</tr>\n<tr style=\"height: 50.3594px;\">\n<td style=\"width: 33.2843%; height: 50.3594px;\"><a href=\"https://adamita.cz\" target=\"_blank\" rel=\"noopener noreferrer\">adamita.cz</a></td>\n<td style=\"width: 33.2843%; height: 50.3594px;\">Nahota, Nudismus (CZ)</td>\n<td style=\"width: 33.2889%; height: 50.3594px;\">0%</td>\n</tr>\n<tr style=\"height: 50.3594px;\">\n<td style=\"width: 33.2843%; height: 50.3594px;\">area-51.cz</td>\n<td style=\"width: 33.2843%; height: 50.3594px;\">Technologie (CZ)</td>\n<td style=\"width: 33.2889%; height: 50.3594px;\">5%</td>\n</tr>\n<tr style=\"height: 50.3594px;\">\n<td style=\"width: 33.2843%; height: 50.3594px;\"><a href=\"https://janrippl.cz\" target=\"_blank\" rel=\"noopener noreferrer\">janrippl.cz</a></td>\n<td style=\"width: 33.2843%; height: 50.3594px;\">Osobní web (CZ)</td>\n<td style=\"width: 33.2889%; height: 50.3594px;\">0%</td>\n</tr>\n<tr style=\"height: 50.3594px;\">\n<td style=\"width: 33.2843%; height: 50.3594px;\"><a href=\"https://nahatej.cz\" target=\"_blank\" rel=\"noopener noreferrer\">nahatej.cz</a></td>\n<td style=\"width: 33.2843%; height: 50.3594px;\">Nahota, Nudismus (CZ)</td>\n<td style=\"width: 33.2889%; height: 50.3594px;\">50%</td>\n</tr>\n<tr style=\"height: 50.3594px;\">\n<td style=\"width: 33.2843%; height: 50.3594px;\"><a href=\"https://nahej.cz\" target=\"_blank\" rel=\"noopener noreferrer\">nahej.cz</a></td>\n<td style=\"width: 33.2843%; height: 50.3594px;\">Nahota, Nudismus (CZ)</td>\n<td style=\"width: 33.2889%; height: 50.3594px;\">0%</td>\n</tr>\n<tr style=\"height: 50.3594px;\">\n<td style=\"width: 33.2843%; height: 50.3594px;\">nechseinspirovat.cz</td>\n<td style=\"width: 33.2843%; height: 50.3594px;\">-</td>\n<td style=\"width: 33.2889%; height: 50.3594px;\">0%</td>\n</tr>\n<tr style=\"height: 50.3594px;\">\n<td style=\"width: 33.2843%; height: 50.3594px;\">nude-in-public.eu</td>\n<td style=\"width: 33.2843%; height: 50.3594px;\">Nahota, Nudismus (CZ)</td>\n<td style=\"width: 33.2889%; height: 50.3594px;\">50%</td>\n</tr>\n<tr>\n<td style=\"width: 33.2843%;\">nudista.online</td>\n<td style=\"width: 33.2843%;\">Nahota, Nudismus (CZ)</td>\n<td style=\"width: 33.2889%;\">75%</td>\n</tr>\n<tr>\n<td style=\"width: 33.2843%;\">obec-mokriny.cz</td>\n<td style=\"width: 33.2843%;\">Web obce</td>\n<td style=\"width: 33.2889%;\">50%</td>\n</tr>\n<tr>\n<td style=\"width: 33.2843%;\">omprela.cz</td>\n<td style=\"width: 33.2843%;\">-</td>\n<td style=\"width: 33.2889%;\">0%</td>\n</tr>\n<tr>\n<td style=\"width: 33.2843%;\">ovmv.cz</td>\n<td style=\"width: 33.2843%;\">-</td>\n<td style=\"width: 33.2889%;\">0%</td>\n</tr>\n<tr>\n<td style=\"width: 33.2843%;\">sekurvavzpamatuj.cz</td>\n<td style=\"width: 33.2843%;\">-</td>\n<td style=\"width: 33.2889%;\">0%</td>\n</tr>\n<tr>\n<td style=\"width: 33.2843%;\">xaktivity.cz</td>\n<td style=\"width: 33.2843%;\">Technologie (CZ)</td>\n<td style=\"width: 33.2889%;\">0%</td>\n</tr>\n</tbody>\n</table>",
            "image": "https://area-51.cz/media/posts/1/a1.png",
            "author": {
                "name": "Jan Rippl"
            },
            "tags": [
                   "Software",
                   "Hardware"
            ],
            "date_published": "2023-06-16T07:00:33+02:00",
            "date_modified": "2023-06-20T01:00:39+02:00"
        }
    ]
}
